.pep8.ini
.pylintrc
CHANGES.rst
MANIFEST.in
README.rst
devbox_version.py
run_autopep8.sh
setup.cfg
setup.py
devbox/__init__.py
devbox/_version.py
devbox/create.py
devbox/hook.py
devbox/unbox.py
devbox/version_helper.py
devbox.egg-info/PKG-INFO
devbox.egg-info/SOURCES.txt
devbox.egg-info/dependency_links.txt
devbox.egg-info/entry_points.txt
devbox.egg-info/not-zip-safe
devbox.egg-info/requires.txt
devbox.egg-info/top_level.txt
devbox/static/gitignore.jinja2
devbox/static/pre-commit.jinja2
devbox/static/python/README.rst.jinja2
devbox/static/python/__init__.py.jinja2
devbox/static/python/autoenv.jinja2
devbox/static/python/gitignore.jinja2
devbox/static/python/pre-commit.jinja2
devbox/static/python/setup.py.jinja2
devbox/static/python/tox.ini.jinja2